pybandstructure/__init__.py
pybandstructure/common.py
pybandstructure/band_structure/__init__.py
pybandstructure/band_structure/band_structure.py
pybandstructure/crystal/__init__.py
pybandstructure/crystal/crystal.py
pybandstructure/crystal/analysis/__init__.py
pybandstructure/crystal/analysis/conductivity_functions.py
pybandstructure/crystal/analysis/dos_functions.py
pybandstructure/crystal/analysis/polarization_functions.py
pybandstructure/geometry/__init__.py
pybandstructure/geometry/crystal_geometry.py
pybandstructure/geometry/point_groups.py
pybandstructure/models/__init__.py
pybandstructure/models/dirac.py
pybandstructure/models/twisted_bilayer.py
pybandstructure/operators/__init__.py
pybandstructure/operators/operators.py
pybandstructure/operators/superlattices/__init__.py
pybandstructure/operators/superlattices/superlattices.py
pybandstructure/sample/__init__.py
pybandstructure/sample/sample.py
pybandstructure-2.1.dist-info/LICENSE.txt
pybandstructure-2.1.dist-info/METADATA
pybandstructure-2.1.dist-info/WHEEL
pybandstructure-2.1.dist-info/top_level.txt
pybandstructure-2.1.dist-info/RECORD
