Metadata-Version: 2.2
Name: pybandstructure
Version: 2.1
Summary: Package for calculating simple band structures and analyzing the results
Home-page: https://gitlab.com/itorre/bandstructure-calculation
Author: Iacopo Torre, Pietro Novelli
Author-email: iacopo.torre@upc.edu
Classifier: Programming Language :: Python :: 3
Classifier: License :: OSI Approved :: GNU Lesser General Public License v3 (LGPLv3)
Classifier: Operating System :: OS Independent
Requires-Python: >=3.6
License-File: LICENSE.txt
Requires-Dist: numpy>=1.18.0
Requires-Dist: scipy
Requires-Dist: matplotlib
Requires-Dist: tqdm
Requires-Dist: h5py
Dynamic: author
Dynamic: author-email
Dynamic: classifier
Dynamic: description
Dynamic: description-content-type
Dynamic: home-page
Dynamic: requires-dist
Dynamic: requires-python
Dynamic: summary
